{
    "summary": {
        "BPU OPs per frame (effective)": 1041126912,
        "BPU OPs per run (effective)": 1041126912,
        "BPU PE number": 1,
        "BPU core number": 2,
        "BPU march": "BERNOULLI2",
        "DDR bytes per frame": 5405184,
        "DDR bytes per run": 5405184,
        "DDR bytes per second": 2686656099,
        "DDR megabytes per frame": 5.155,
        "DDR megabytes per run": 5.155,
        "DDR megabytes per second": 2562.2,
        "FPS": 497.05,
        "HBDK version": "3.48.6",
        "compiling options": "-f hbir -m /tmp/tmpmw_vs5zr/torch-jit-export_subgraph_5.hbir -o /tmp/tmpmw_vs5zr/torch-jit-export_subgraph_5.hbm --march bernoulli2 --progressbar --O3 --core-num 2 --fast --input-layout NHWC --output-layout NCHW --input-source ddr,ddr,ddr",
        "frame per run": 1,
        "frame per second": 497.05,
        "input features": [
            [
                "input name",
                "input size"
            ],
            [
                "382_calibrated_quantized",
                "1x21x21x256"
            ],
            [
                "375_quantized",
                "1x21x21x256"
            ],
            [
                "387_quantized",
                "1x21x21x256"
            ]
        ],
        "interval computing unit utilization": [
            0.061,
            0.0,
            0.287,
            0.116,
            0.113,
            0.0,
            1.463,
            1.996,
            1.995,
            1.884,
            1.994,
            1.995,
            1.893,
            1.886,
            1.995,
            1.944,
            1.935,
            1.996,
            1.857,
            0.996,
            0.095
        ],
        "interval computing units utilization": [
            0.061,
            0.0,
            0.287,
            0.116,
            0.113,
            0.0,
            1.463,
            1.996,
            1.995,
            1.884,
            1.994,
            1.995,
            1.893,
            1.886,
            1.995,
            1.944,
            1.935,
            1.996,
            1.857,
            0.996,
            0.095
        ],
        "interval loading bandwidth (megabytes/s)": [
            1879,
            1636,
            2287,
            2234,
            1096,
            1026,
            3520,
            3259,
            585,
            3320,
            3398,
            1203,
            2539,
            2741,
            1343,
            1874,
            3383,
            1914,
            117,
            0,
            0
        ],
        "interval number": 21,
        "interval storing bandwidth (megabytes/s)": [
            1640,
            820,
            0,
            546,
            820,
            273,
            193,
            579,
            744,
            709,
            732,
            820,
            791,
            703,
            703,
            703,
            703,
            791,
            820,
            556,
            234
        ],
        "interval time (ms)": 0.1,
        "latency (ms)": 2.01,
        "latency (ms) by segments": [
            0.093,
            0.301,
            1.418
        ],
        "latency (us)": 2011.9,
        "loaded bytes per frame": 4028928,
        "loaded bytes per run": 4028928,
        "model json CRC": "568c3b8c",
        "model json file": "/tmp/tmpmw_vs5zr/torch-jit-export_subgraph_5.hbir",
        "model name": "torch-jit-export_subgraph_5",
        "model param CRC": "00000000",
        "multicore sync time (ms)": 0.4,
        "run per second": 497.05,
        "runtime version": "3.15.40.0",
        "stored bytes per frame": 1376256,
        "stored bytes per run": 1376256,
        "worst FPS": 497.05
    }
}
